hexdoor/__init__.py
hexdoor/main.py
hexdoor-0.1.0.dist-info/LICENSE
hexdoor-0.1.0.dist-info/METADATA
hexdoor-0.1.0.dist-info/WHEEL
hexdoor-0.1.0.dist-info/entry_points.txt
hexdoor-0.1.0.dist-info/top_level.txt
hexdoor-0.1.0.dist-info/RECORD
