Metadata-Version: 2.1
Name: hexdoor
Version: 0.1.0
Summary: A colorful terminal hex viewer
Home-page: https://github.com/sinofp/hexdoor
Author: sinofp
License: WTFPL
Keywords: hex viewer
Platform: UNKNOWN
Classifier: Programming Language :: Python :: 3
Classifier: License :: Other/Proprietary License
Classifier: Operating System :: OS Independent
Requires-Dist: colorama
Requires-Dist: fire
